icx_reward/__init__.py
icx_reward/cli.py
icx_reward/commands.py
icx_reward/penalty.py
icx_reward/reward.py
icx_reward/rpc.py
icx_reward/utils.py
icx_reward/vote.py
icx_reward/types/__init__.py
icx_reward/types/address.py
icx_reward/types/argparse_type.py
icx_reward/types/bloom.py
icx_reward/types/constants.py
icx_reward/types/event.py
icx_reward/types/exception.py
icx_reward/types/prep.py
icx_reward/types/rate.py
icx_reward/types/reward_fund.py
icx_reward/types/rlp.py
icx_reward/types/term.py
icx_reward/types/utils.py
icx_reward-0.7.0.dist-info/LICENSE
icx_reward-0.7.0.dist-info/METADATA
icx_reward-0.7.0.dist-info/WHEEL
icx_reward-0.7.0.dist-info/entry_points.txt
icx_reward-0.7.0.dist-info/top_level.txt
icx_reward-0.7.0.dist-info/RECORD
