Metadata-Version: 2.1
Name: icx_reward
Version: 0.7.0
Summary: Tools for ICON reward
Author-email: ICON Foundation <foo@icon.foundation>
Project-URL: Homepage, https://github.com/icon-project/icx-reward
Project-URL: Bug Tracker, https://github.com/icon-project/icx-reward/issues
Classifier: Programming Language :: Python :: 3
Classifier: License :: OSI Approved :: Apache Software License
Classifier: Operating System :: OS Independent
Requires-Python: >=3.9
License-File: LICENSE
